tiledb_vector_search-0.15.0.dist-info/RECORD
tiledb_vector_search-0.15.0.dist-info/WHEEL
tiledb_vector_search-0.15.0.dist-info/METADATA
tiledb_vector_search-0.15.0.dist-info/licenses/LICENSE
tiledb/vector_search/ivf_flat_index.py
tiledb/vector_search/ingestion.py
tiledb/vector_search/module.cc
tiledb/vector_search/version.py
tiledb/vector_search/index.py
tiledb/vector_search/ivf_pq_index.py
tiledb/vector_search/storage_formats.py
tiledb/vector_search/__init__.py
tiledb/vector_search/utils.py
tiledb/vector_search/kmeans.cc
tiledb/vector_search/_tiledbvspy.cpython-313-darwin.so
tiledb/vector_search/module.py
tiledb/vector_search/flat_index.py
tiledb/vector_search/type_erased_module.cc
tiledb/vector_search/vamana_index.py
tiledb/vector_search/embeddings/huggingface_auto_image_embedding.py
tiledb/vector_search/embeddings/colpali_embedding.py
tiledb/vector_search/embeddings/image_resnetv2_embedding.py
tiledb/vector_search/embeddings/soma_geneptw_embedding.py
tiledb/vector_search/embeddings/random_embedding.py
tiledb/vector_search/embeddings/__init__.py
tiledb/vector_search/embeddings/langchain_embedding.py
tiledb/vector_search/embeddings/sentence_transformers_embedding.py
tiledb/vector_search/embeddings/soma_scvi_embedding.py
tiledb/vector_search/embeddings/object_embedding.py
tiledb/vector_search/embeddings/soma_scgpt_embedding.py
tiledb/vector_search/include/experimental/__p0009_bits/full_extent_t.hpp
tiledb/vector_search/include/experimental/__p0009_bits/layout_stride.hpp
tiledb/vector_search/include/experimental/__p0009_bits/layout_left.hpp
tiledb/vector_search/include/experimental/__p0009_bits/utility.hpp
tiledb/vector_search/include/experimental/__p0009_bits/dynamic_extent.hpp
tiledb/vector_search/include/experimental/__p0009_bits/macros.hpp
tiledb/vector_search/include/experimental/__p0009_bits/config.hpp
tiledb/vector_search/include/experimental/__p0009_bits/trait_backports.hpp
tiledb/vector_search/include/experimental/__p0009_bits/no_unique_address.hpp
tiledb/vector_search/include/experimental/__p0009_bits/type_list.hpp
tiledb/vector_search/include/experimental/__p0009_bits/default_accessor.hpp
