Metadata-Version: 2.2
Name: tiledb-vector-search
Version: 0.15.0
Summary: TileDB Vector Search Python client
License: MIT
Classifier: Development Status :: 4 - Beta
Classifier: License :: OSI Approved :: MIT License
Classifier: Programming Language :: Python :: 3 :: Only
Classifier: Programming Language :: Python :: 3.9
Classifier: Programming Language :: Python :: 3.10
Classifier: Programming Language :: Python :: 3.11
Classifier: Programming Language :: Python :: 3.12
Classifier: Programming Language :: Python :: 3.13
Project-URL: homepage, https://tiledb.com
Project-URL: repository, https://github.com/TileDB-Inc/tiledb-vector-search
Requires-Python: ~=3.9
Requires-Dist: tiledb-cloud>=0.11
Requires-Dist: tiledb>=0.35.1
Requires-Dist: typing-extensions
Requires-Dist: scikit-learn
Requires-Dist: numpy>=1.25.0
Provides-Extra: test
Requires-Dist: nbmake; extra == "test"
Requires-Dist: pytest<8.0.0; extra == "test"
Requires-Dist: pytest-xdist; extra == "test"
Provides-Extra: formatting
Requires-Dist: pre-commit; extra == "formatting"
Provides-Extra: benchmarks
Requires-Dist: boto3; extra == "benchmarks"
Requires-Dist: paramiko; extra == "benchmarks"
Requires-Dist: matplotlib; extra == "benchmarks"
